{
  "project_info": {
    "project_number": "692591629915",
    "firebase_url": "https://fireapp-d0c9e.firebaseio.com",
    "project_id": "fireapp-d0c9e",
    "storage_bucket": "fireapp-d0c9e.appspot.com"
  },
  "client": [
    {
      "client_info": {
        "mobilesdk_app_id": "1:692591629915:android:a7a03df831ae4a2e",
        "android_client_info": {
          "package_name": "com.example.android.fireapp"
        }
      },
      "oauth_client": [
        {
          "client_id": "692591629915-5cr1v1hahl4p69g42df6g4eedvie8kdv.apps.googleusercontent.com",
          "client_type": 1,
          "android_info": {
            "package_name": "com.example.android.fireapp",
            "certificate_hash": "15eee2a86e93e6347d6b05cc9e1a74ef561f9adc"
          }
        },
        {
          "client_id": "692591629915-qfaev0591hjs9if34h0kkiujguflj880.apps.googleusercontent.com",
          "client_type": 3
        }
      ],
      "api_key": [
        {
          "current_key": "AIzaSyCzqXJd5yvFlI2ZMp3KHd17mettaUIDUz0"
        }
      ],
      "services": {
        "analytics_service": {
          "status": 1
        },
        "appinvite_service": {
          "status": 2,
          "other_platform_oauth_client": [
            {
              "client_id": "692591629915-qfaev0591hjs9if34h0kkiujguflj880.apps.googleusercontent.com",
              "client_type": 3
            }
          ]
        },
        "ads_service": {
          "status": 2
        }
      }
    }
  ],
  "configuration_version": "1"
}